hack4u/__init__.py
hack4u/courses.py
hack4u/utils.py
comvxie-0.5.0.dist-info/METADATA
comvxie-0.5.0.dist-info/WHEEL
comvxie-0.5.0.dist-info/top_level.txt
comvxie-0.5.0.dist-info/RECORD
