Metadata-Version: 2.4
Name: ComVxie
Version: 0.5.0
Summary: Library to consult courses about Hack4u
Home-page: https://hack4u.io
Author: Vxie
Dynamic: author
Dynamic: description
Dynamic: description-content-type
Dynamic: home-page
Dynamic: summary
